{
  "dishes": [
    {
      "id": "34343",
      "poster": "https://avatars3.githubusercontent.com/u/72467?v=4&s=460",
      "name": "黑森林",
      "price": 42,
      "desc": "来自德国"
    },
    {
      "name": "芝士",
      "desc": "yummy",
      "price": "12",
      "poster": "https://avatars3.githubusercontent.com/u/72467?v=4&s=460",
      "id": "ryZuH5OjZ"
    },
    {
      "name": "抹茶",
      "desc": "好吃",
      "price": "12",
      "poster": "https://avatars3.githubusercontent.com/u/72467?v=4&s=460",
      "id": "Hk5CHq_jb"
    }
  ]
}